{
  "id": "https://id.oclc.org/worldcat/ddc/E3jvBPhjpj6bXhpFG9j4tt6xgf",
  "notation": "966",
  "created": "1996-06-01",
  "prefLabel": {
    "sv": "Västafrika och öar utanför kusten",
    "de": "Westafrika und vorgelagerte Inseln",
    "en": "West Africa and offshore islands",
    "fr": "Afrique occidentale et îles au large",
    "no": "Vest-Afrika og øyene utenfor kysten",
    "it": "Africa occidentale e isole al largo"
  },
  "inScheme": "https://id.oclc.org/worldcat/ddc/",
  "type": "Concept",
  "modified": "2024-07-25T12:09:51Z",
  "broader": "https://id.oclc.org/worldcat/ddc/E47h3KMHqTWYwm8C373XBYgQJW",
  "@context": "https://id.oclc.org/worldcat/ddc/context.json"
}