{
  "id": "https://id.oclc.org/worldcat/ddc/E3rKG7Vq8rKT7b7cVF9HCVbqB7",
  "modified": "2025-05-12T11:52:46Z",
  "inScheme": "https://id.oclc.org/worldcat/ddc/",
  "prefLabel": {
    "en": "Private law",
    "it": "Diritto privato",
    "sv": "Civilrätt (privaträtt)",
    "de": "Privatrecht",
    "fr": "Droit privé",
    "no": "Privatrett"
  },
  "notation": "346",
  "broader": "https://id.oclc.org/worldcat/ddc/E36V4gYgV8DTGVG8BCTcDqKfVf",
  "type": "Concept",
  "created": "1996-06-01",
  "@context": "https://id.oclc.org/worldcat/ddc/context.json"
}